ud3tn_utils/__init__.py
ud3tn_utils/config.py
ud3tn_utils/aap/__init__.py
ud3tn_utils/aap/aap_client.py
ud3tn_utils/aap/aap_message.py
ud3tn_utils/aap/bin/__init__.py
ud3tn_utils/aap/bin/aap_config.py
ud3tn_utils/aap/bin/aap_contact_plan_reader.py
ud3tn_utils/aap/bin/aap_echo.py
ud3tn_utils/aap/bin/aap_ping.py
ud3tn_utils/aap/bin/aap_receive.py
ud3tn_utils/aap/bin/aap_send.py
ud3tn_utils/aap/bin/aap_send_and_receive.py
ud3tn_utils/aap/bin/helpers.py
ud3tn_utils/aap2/__init__.py
ud3tn_utils/aap2/aap2_client.py
ud3tn_utils/aap2/bin/__init__.py
ud3tn_utils/aap2/bin/aap2_bdm_static.py
ud3tn_utils/aap2/bin/aap2_bdm_ud3tn_routing.py
ud3tn_utils/aap2/bin/aap2_config.py
ud3tn_utils/aap2/bin/aap2_configure_link.py
ud3tn_utils/aap2/bin/aap2_ping.py
ud3tn_utils/aap2/bin/aap2_receive.py
ud3tn_utils/aap2/bin/aap2_send.py
ud3tn_utils/aap2/bin/aap2_storage_agent.py
ud3tn_utils/aap2/bin/helpers.py
ud3tn_utils/aap2/generated/__init__.py
ud3tn_utils/aap2/generated/aap2_pb2.py
ud3tn_utils/storage_agent/__init__.py
ud3tn_utils/storage_agent/generated/storage_agent_pb2.py
ud3tn_utils-0.14.5.dist-info/licenses/LICENSE
ud3tn_utils-0.14.5.dist-info/METADATA
ud3tn_utils-0.14.5.dist-info/WHEEL
ud3tn_utils-0.14.5.dist-info/entry_points.txt
ud3tn_utils-0.14.5.dist-info/top_level.txt
ud3tn_utils-0.14.5.dist-info/RECORD
