Metadata-Version: 2.4
Name: ud3tn-utils
Version: 0.14.5
Summary: μD3TN Utilities
Author-email: D3TN GmbH <contact@d3tn.com>
License: BSD-3-Clause OR Apache-2.0
Project-URL: Repository, https://gitlab.com/d3tn/ud3tn
Requires-Python: >=3.9
License-File: LICENSE
Requires-Dist: cbor2==5.6.5
Requires-Dist: jsonschema==4.23.0
Requires-Dist: protobuf==6.30.2
Requires-Dist: pyd3tn==0.14.5
Dynamic: license-file
